<?xml version="1.0" encoding="UTF-8" standalone="yes" ?>
<weather reset="1" enable="1">
    <overcast>
        <current actual="0.4" time="120" duration="240" />
        <limits min="0.1" max="1.0" />
        <timelimits min="600" max="900" />
        <changelimits min="0.0" max="0.8" />
    </overcast>
    <fog>
        <current actual="0.1" time="120" duration="240" />
        <limits min="0.1" max="0.35" />
        <timelimits min="900" max="900" />
        <changelimits min="0.1" max="0.35" />
    </fog>
    <rain>
        <current actual="0.0" time="120" duration="240" />
        <limits min="0.0" max="0.4" />
        <timelimits min="300" max="600" />
        <changelimits min="0.0" max="0.4" />
        <thresholds min="0.98" max="1.0" end="45" />
    </rain>
    <windMagnitude>
        <current actual="8.0" time="120" duration="240" />
        <limits min="0.0" max="20.0" />
        <timelimits min="120" max="240" />
        <changelimits min="0.0" max="5.0" />
    </windMagnitude>
    <windDirection>
        <current actual="0.0" time="120" duration="240" />
        <limits min="-3.14" max="3.14" />
        <timelimits min="60" max="120" />
        <changelimits min="-1.0" max="1.0" />
    </windDirection>
    <snowfall>
        <current actual="0.0" time="0" duration="32768" />
        <limits min="0.0" max="0.0" />
        <timelimits min="300" max="3600" />
        <changelimits min="0.0" max="0.0" />
        <thresholds min="1.0" max="1.0" end="120" />
    </snowfall>
    <storm density="0.4" threshold="0.8" timeout="80"/>
</weather>